tcrcloud/TCRcloud.py
tcrcloud/__init__.py
tcrcloud/aminoacids.py
tcrcloud/cloud.py
tcrcloud/colours.py
tcrcloud/download.py
tcrcloud/format.py
tcrcloud/radar.py
tcrcloud/testdata.py
tcrcloud/vgenes.py
TCRcloud-1.5.0.dist-info/LICENSE
TCRcloud-1.5.0.dist-info/METADATA
TCRcloud-1.5.0.dist-info/WHEEL
TCRcloud-1.5.0.dist-info/entry_points.txt
TCRcloud-1.5.0.dist-info/top_level.txt
TCRcloud-1.5.0.dist-info/RECORD
