Metadata-Version: 2.1
Name: TCRcloud
Version: 1.5.0
Summary: TCRcloud is an AIRR visualization and comparison tool
Home-page: https://github.com/eriicdesousa/TCRcloud
Author: Eric de Sousa
Author-email: eric.desousa@research.fchampalimaud.org
Project-URL: Bug Tracker, https://github.com/eriicdesousa/TCRcloud/issues
Classifier: Programming Language :: Python :: 3 :: Only
Classifier: Programming Language :: Python :: 3.10
Classifier: Programming Language :: Python :: 3.11
Classifier: Programming Language :: Python :: 3.12
Classifier: License :: OSI Approved :: MIT License
Classifier: Operating System :: OS Independent
Classifier: Intended Audience :: Science/Research
Requires-Python: >=3.10
License-File: LICENSE
Requires-Dist: airr >=1.5.0
Requires-Dist: numpy >=1.9.2
Requires-Dist: scipy >=1.3.0
Requires-Dist: matplotlib >=3.7.0
Requires-Dist: plotly >=5.18.0
Requires-Dist: wordcloud
Requires-Dist: pandas
Requires-Dist: scikit-learn
Requires-Dist: scikit-bio
Requires-Dist: requests
Requires-Dist: kaleido
